{"noiseKey":{"private":{"type":"Buffer","data":"wBb1e/2HnQ7a+oIaSxIY/7AZOsNi42E2za8dP6Wd718="},"public":{"type":"Buffer","data":"yi1KhJ0eFu1p7+eyuIZ92KRbyGZzvSSXlOqJovUczBk="}},"pairingEphemeralKeyPair":{"private":{"type":"Buffer","data":"kJpQKSg5UOe+6w4BOkCQtIftYrwyEqY4JJPxrGTuJns="},"public":{"type":"Buffer","data":"lv5zUB7JieowbWsZOa26cpgnhSMd3S9O34OhjHRzIXo="}},"signedIdentityKey":{"private":{"type":"Buffer","data":"CKQNOSQFOLR7mFacDb43O/8FEAu51FKdjbnjMPc14WU="},"public":{"type":"Buffer","data":"aD9+qMt7JH300h9epQBp6ab7SDX1iOI5uLJgGzpBIDY="}},"signedPreKey":{"keyPair":{"private":{"type":"Buffer","data":"yGSpj/CuFLVEX+fAFctz7yYyRNOPMdz7rQMldmAkCFI="},"public":{"type":"Buffer","data":"1lc9z963IfY0ytSIf4ZB7ck+DcnYFE7e9/1zunizl3M="}},"signature":{"type":"Buffer","data":"r613OTB24DpuE2gPGEPF65zPtQxagDPWpEbbiO7p+8llfc5FuVVle8g9IBrBMBtY2n/8QZBGUA04WbQP6gUXig=="},"keyId":1},"registrationId":208,"advSecretKey":"aCnmFoNYFCpGKbZZZwSPlBigQl1IsLnZEPBixJUm/E0=","processedHistoryMessages":[{"key":{"remoteJid":"558189556592@s.whatsapp.net","fromMe":false,"id":"2A838208EB952196A875","participant":"","addressingMode":"pn"},"messageTimestamp":1774968134},{"key":{"remoteJid":"558189556592@s.whatsapp.net","fromMe":false,"id":"2A77C823EC11E00F9A2B","participant":"","addressingMode":"pn"},"messageTimestamp":1774968146},{"key":{"remoteJid":"558189556592@s.whatsapp.net","fromMe":false,"id":"2A79D410C3E55F4DBDEF","participant":"","addressingMode":"pn"},"messageTimestamp":1774968148},{"key":{"remoteJid":"558189556592@s.whatsapp.net","fromMe":false,"id":"2A0290347E3A21349161","participant":"","addressingMode":"pn"},"messageTimestamp":1774968148},{"key":{"remoteJid":"558189556592@s.whatsapp.net","fromMe":false,"id":"2A1FE2574E9C759FA122","participant":"","addressingMode":"pn"},"messageTimestamp":1774968164},{"key":{"remoteJid":"558189556592@s.whatsapp.net","fromMe":false,"id":"2A5B4DE28C8B78652780","participant":"","addressingMode":"pn"},"messageTimestamp":1774968219}],"nextPreKeyId":813,"firstUnuploadedPreKeyId":813,"accountSyncCounter":1,"accountSettings":{"unarchiveChats":false},"registered":false,"account":{"details":"CLr5/+YCELy6r84GGAggACgA","accountSignatureKey":"FpqSgzbsrXXBifyW+//IzFM6YOSDLv3iPjDCbiIpozk=","accountSignature":"FH1Mb0BP3lnz4e40d14HnRRA/mZFy3u//WC8wFlUnvy3iu9n0cBGeZWYBbs2pGRN7RZ91/LDtHUS6ivceM77gQ==","deviceSignature":"//LgofKhg2Ow3S7338lL3NZLysC5SFeeFltK1M63HW3rXo6hlAswdDS9YUlf4eUb/qo4V08np2wkmWJ46CX+gA=="},"me":{"id":"558189556592:80@s.whatsapp.net","name":"Pedro Aguiar","lid":"277527985705054:80@lid"},"signalIdentities":[{"identifier":{"name":"277527985705054:80@lid","deviceId":0},"identifierKey":{"type":"Buffer","data":"BRaakoM27K11wYn8lvv/yMxTOmDkgy794j4wwm4iKaM5"}}],"platform":"smbi","routingInfo":{"type":"Buffer","data":"CA0ICAgS"},"lastAccountSyncTimestamp":1774968131,"myAppStateKeyId":"AAAAAPg9","lastPropHash":"3ml1jS"}